symphonypy/__init__.py
symphonypy/_utils.py
symphonypy/datasets.py
symphonypy/pp.py
symphonypy/tl.py
symphonypy-0.2.2.dist-info/licenses/LICENSE
symphonypy-0.2.2.dist-info/METADATA
symphonypy-0.2.2.dist-info/WHEEL
symphonypy-0.2.2.dist-info/top_level.txt
symphonypy-0.2.2.dist-info/RECORD
