Metadata-Version: 2.4
Name: symphonypy
Version: 0.2.2
Summary: Porting of Symphony R package to Python
Home-page: https://github.com/potulabe/symphonypy
Author: Kseniya Petrova, Sergey Isaev
Author-email: praefrontalis@gmail.com, serj.hoop@gmail.com
Classifier: Programming Language :: Python :: 3
Classifier: License :: OSI Approved :: MIT License
Classifier: Operating System :: OS Independent
Requires-Python: >=3.8
License-File: LICENSE
Requires-Dist: harmonypy
Requires-Dist: scanpy
Requires-Dist: scikit-learn
Dynamic: license-file
